plotly_for_scanpy/__init__.py
plotly_for_scanpy/dynamic_downsampling.py
plotly_for_scanpy/one_light_template.py
plotly_for_scanpy/pl.py
plotly_for_scanpy-0.1.0.dist-info/licenses/LICENSE
plotly_for_scanpy-0.1.0.dist-info/METADATA
plotly_for_scanpy-0.1.0.dist-info/WHEEL
plotly_for_scanpy-0.1.0.dist-info/top_level.txt
plotly_for_scanpy-0.1.0.dist-info/RECORD
