Metadata-Version: 2.4
Name: plotly_for_scanpy
Version: 0.1.0
Summary: Plotly-based visualization tools for Scanpy data
Author-email: Klim Kostiuk <2601074@gmail.com>
License: MIT License
Project-URL: Homepage, https://github.com/yourusername/plotly_for_scanpy
Project-URL: Bug Tracker, https://github.com/yourusername/plotly_for_scanpy/issues
Project-URL: Documentation, https://colab.research.google.com/drive/1pHt8m-wIVS2B7aUbjrlsNrNWV2JsEI-E
Classifier: Programming Language :: Python :: 3
Classifier: License :: OSI Approved :: MIT License
Classifier: Operating System :: OS Independent
Classifier: Topic :: Scientific/Engineering :: Visualization
Classifier: Topic :: Scientific/Engineering :: Bio-Informatics
Requires-Python: >=3.7
License-File: LICENSE
Requires-Dist: numpy
Requires-Dist: pandas
Requires-Dist: plotly>=5.0.0
Requires-Dist: dash
Requires-Dist: scipy
Requires-Dist: anndata
Requires-Dist: webcolors
Dynamic: license-file
